{
  "41377": "evening",
  "41384": "evening",
  "41391": "evening",
  "41401": "evening",
  "45827": "evening",
  "45828": "evening",
  "45829": "evening",
  "45830": "evening",
  "45831": "evening",
  "45832": "evening",
  "45834": "evening",
  "45835": "evening",
  "45836": "evening",
  "45838": "evening",
  "45839": "evening",
  "45840": "evening",
  "45841": "evening",
  "45842": "evening",
  "45843": "evening",
  "45845": "evening",
  "45846": "evening",
  "45847": "evening",
  "45849": "evening",
  "45850": "evening",
  "45851": "evening",
  "45853": "evening",
  "45854": "evening",
  "45855": "evening",
  "45857": "evening",
  "45858": "evening",
  "45860": "evening",
  "45861": "evening",
  "45863": "evening",
  "45864": "evening",
  "45865": "evening",
  "45866": "evening",
  "49476": "evening",
  "49477": "evening",
  "49478": "evening",
  "49479": "evening",
  "49480": "evening",
  "49481": "evening",
  "49482": "evening",
  "49483": "evening",
  "49484": "evening",
  "49485": "evening",
  "49486": "evening",
  "49487": "evening",
  "49488": "evening",
  "49489": "evening",
  "49490": "evening",
  "49491": "evening",
  "49492": "evening",
  "49493": "evening",
  "49494": "evening"
}
